GaodengshuxueJiangyiZhiJifenBiaoGongshiTuidaoDanielLau/README.md
GaodengshuxueJiangyiZhiJifenBiaoGongshiTuidaoDanielLau/__init__.py
GaodengshuxueJiangyiZhiJifenBiaoGongshiTuidaoDanielLau/__main__.py
GaodengshuxueJiangyiZhiJifenBiaoGongshiTuidaoDanielLau/file.pdf
GaodengshuxueJiangyiZhiJifenBiaoGongshiTuidaoDanielLau/index.html
gaodengshuxue_jiangyi_zhi_jifen_biao_gongshi_tuidao_daniel_lau-2024.3.2.0.dist-info/METADATA
gaodengshuxue_jiangyi_zhi_jifen_biao_gongshi_tuidao_daniel_lau-2024.3.2.0.dist-info/WHEEL
gaodengshuxue_jiangyi_zhi_jifen_biao_gongshi_tuidao_daniel_lau-2024.3.2.0.dist-info/entry_points.txt
gaodengshuxue_jiangyi_zhi_jifen_biao_gongshi_tuidao_daniel_lau-2024.3.2.0.dist-info/top_level.txt
gaodengshuxue_jiangyi_zhi_jifen_biao_gongshi_tuidao_daniel_lau-2024.3.2.0.dist-info/RECORD
